{
  "operador": "entel",
  "total_comentarios": 3052,
  "positivo": {
    "muchas gracias entel perú": 6,
    "señal power que llega": 4,
    "y39 5g desde": 3,
    "funciona espectacular": 3,
    "descontar el precio": 2,
    "precio que costó": 2,
    "compre no uso internet": 2,
    "uso internet en casa": 2,
    "celular en muy bueno": 2,
    "entel también ofrecemos equipos": 2,
    "simplemente funciona": 2,
    "equipazo por dónde": 2,
    "alianza entre entel": 2,
    "plan power también disfrutas": 2,
    "whatsapp ilimitado sería bueno": 2,
    "llevar una señal power": 2,
    "señal power que llegue": 2,
    "demás requisitos que necesitas": 2,
    "turismo rutear buena señal": 2,
    "hoy es hoy bitel": 2,
    "comentario sobre la cobertura": 2,
    "mejora en nuestra red": 2,
    "nuestra red y brindar": 2,
    "fuiste parte de entel": 2,
    "entel por siempre": 2,
    "nuestros entel lovers": 2,
    "conexión que acompañe": 2,
    "buen servicio y equipazo": 2,
    "gran precio y disfruta": 2,
    "entel valoramos las opiniones": 2,
    "mejor conexión": 2,
    "somos una señal power": 2,
    "disfrutes de nuestra señal": 2,
    "tus datos al inbox": 2,
    "mejor para nuestros entel": 2,
    "disfrutes de tu señal": 2,
    "celular es bueno": 2,
    "app mi entel perú": 2,
    "servicio confiable": 2,
    "nuestra alianza con starlink": 2
  },
  "negativo": {
    "subieron el costo": 27,
    "costo del plan": 15,
    "señal de mi celular": 14,
    "costo de mi plan": 9,
    "volvieron lo mismo a movistar": 8,
    "terrible señal y lo peor": 8,
    "internet de entel": 7,
    "subieron el costo del plan": 7,
    "plan sin mi autorización": 7,
    "señal de internet": 6,
    "nuevamente me subieron el costo": 6,
    "entel y me enviaron": 6,
    "enviaron un qr usado": 6,
    "servicio da boleta": 6,
    "solución a un problema": 6,
    "formalizar el reclamo ante": 6,
    "señal de entel": 5,
    "va la señal": 5,
    "cambien a entel": 5,
    "contratas el servicio": 5,
    "funciona pienso": 4,
    "experiencia con nuestra señal": 4,
    "sus alrededores la señal": 4,
    "llamar pésimo servicio dejen": 4,
    "dice entel": 4,
    "entel tiene el peor servicio": 4,
    "operadores para hacer un reclamo": 4,
    "abones sin reclamo": 4,
    "abones sin reclamo alguno": 4,
    "entel no cumple": 4,
    "entel y me dijeron": 4,
    "tenia 3 líneas con movistar": 4,
    "servicio y atención": 4,
    "servicio y atención al cliente": 4,
    "velocidad de internet deja": 4,
    "velocidad de internet deja mucho": 4,
    "internet deja mucho que desear": 4,
    "tres líneas hacia entel": 4,
    "logo de entel": 4,
    "entel en el teléfono": 4
  },
  "neutral": {
    "app mi entel perú": 66,
    "inbox con tus datos": 21,
    "plan power ilim": 18,
    "cumples con los requisitos": 16,
    "desde tu app mi entel": 14,
    "zonas sin cobertura móvil": 12,
    "tus datos al inbox": 12,
    "inbox y revisaremos tu señal": 11,
    "precio del equipo dependerá": 10,
    "entel perú si cumples": 10,
    "inconveniente de señal": 10,
    "entel con 2 líneas": 10,
    "zonas sin cobertura móvil terrestre": 9,
    "sucedido con tu señal": 9,
    "desde la app mi entel": 9,
    "déjanos tus datos": 8,
    "plan power s 59": 8,
    "revisaremos tu señal pronto": 8,
    "experiencia con nuestra señal": 8,
    "escríbenos con tus datos": 8,
    "señal power": 7,
    "precio de s 799": 7,
    "desde el plan power": 7,
    "desde el plan power ilim": 7,
    "precio del motorola g67": 6,
    "equipazo tiene el precio": 6,
    "entel o un iphone": 6,
    "desde la web a entel": 6,
    "requisitos para disfrutar": 6,
    "meses desde el plan power": 6,
    "pe o en tiendas entel": 6,
    "tus datos para brindarte": 6,
    "disfrutes de nuestra señal": 6,
    "precio dependerá": 5,
    "precio dependerá de tu evaluación": 5,
    "sms desde planes s 29": 5,
    "entel perú conectividad satelital": 5,
    "plan power desde": 5,
    "volte y roaming activos": 5,
    "inconveniente de señal que estás": 5
  },
  "informativo": {
    "app mi entel perú": 8,
    "celular online a entel": 8,
    "entel y nunca": 8,
    "queja está resuelta": 6,
    "señores entel cómo es posible": 6,
    "entel cómo es posible hace": 6,
    "uds dicen vaya al servicio": 6,
    "dicen vaya al servicio técnico": 6,
    "inconveniente de señal": 5,
    "responsabilizan te envían al servicio": 5,
    "envían al servicio técnico": 5,
    "entel perú y ve": 4,
    "inbox con tus datos": 4,
    "queja por no cumplir": 4,
    "están cambiando de plan": 4,
    "online a entel y nunca": 4,
    "nadie da solución cortan llamadas": 4,
    "cortan llamadas o no saben": 4,
    "entel van a responder": 4,
    "plan de internet": 4,
    "internet y telefonia": 4,
    "aseguremos esos requisitos faltantes": 3,
    "entel puede controlar a sus": 3,
    "dicen que es de entel": 3,
    "sus trabajadores ni las llamadas": 3,
    "llamadas que hacen": 3,
    "llamadas que hacen creo": 3,
    "operador a entel": 3,
    "app los datos": 3,
    "equipazo llega con 5g": 2,
    "5g para que disfrutes": 2,
    "disfrutas de la señal power": 2,
    "amoled y full velocidad 5g": 2,
    "día y velocidad 5g": 2,
    "señal para que conozcas": 2,
    "desde hace cuánto disfrutas": 2,
    "cuánto disfrutas de la señalpower": 2,
    "samsung a56 5g": 2,
    "cartera de lazo dónde": 2,
    "desde tu app mi entel": 2
  },
  "irrelevante": {
    "vivo muy bueno": 3,
    "dónde": 3,
    "bueno y en batería": 2,
    "funciona apenas 5 años": 2,
    "moto edge": 2,
    "único bueno del vivo": 2,
    "detalles sobre cómo acceder": 2,
    "dan una ventaja excelente": 2,
    "ventaja excelente al momento": 2,
    "bicicleta tiene el costo": 2,
    "app no está funcionando": 2,
    "pronto esté disponible": 2,
    "cuéntanos cómo podemos ayudarte": 2,
    "funciona probamos nosotros": 2,
    "batería cuánto": 2,
    "recomiendo perú": 2,
    "increíble": 2,
    "malo": 2,
    "qr": 1,
    "perfecto": 1,
    "genial": 1,
    "móvil": 1
  }
}